django_admin_logs_viewer/__init__.py
django_admin_logs_viewer/apps.py
django_admin_logs_viewer/conf.py
django_admin_logs_viewer/context_processors.py
django_admin_logs_viewer/defaults.py
django_admin_logs_viewer/signals.py
django_admin_logs_viewer/urls.py
django_admin_logs_viewer/templates/admin/base.html
django_admin_logs_viewer/templates/admin/errors.html
django_admin_logs_viewer/templates/admin/logs_dir.html
django_admin_logs_viewer/templates/admin/logs_file.html
django_admin_logs_viewer/views/__init__.py
django_admin_logs_viewer/views/logs_view.py
django_admin_logs_viewer/views/parser.py
django_admin_logs_viewer/views/utils.py
django_admin_logs_viewer-1.1.0.dist-info/licenses/LICENSE
django_admin_logs_viewer-1.1.0.dist-info/METADATA
django_admin_logs_viewer-1.1.0.dist-info/WHEEL
django_admin_logs_viewer-1.1.0.dist-info/top_level.txt
django_admin_logs_viewer-1.1.0.dist-info/RECORD
