Metadata-Version: 2.4
Name: django-admin-logs-viewer
Version: 1.1.0
Summary: A Django admin extension for displaying log files directly from the admin panel.
Author-email: Aleksander Wojsz <wojszalek@gmail.com>
License-Expression: MIT
Project-URL: Homepage, https://github.com/AleksanderWojsz/django-admin-logs-viewer
Classifier: Framework :: Django
Classifier: Intended Audience :: Developers
Classifier: Operating System :: OS Independent
Classifier: Programming Language :: Python
Classifier: Programming Language :: Python :: 3
Requires-Python: >=3.10
License-File: LICENSE
Requires-Dist: Django>=5.2
Requires-Dist: pytz>=2020.0
Dynamic: license-file
